medutils/__init__.py
medutils/complex.py
medutils/io.py
medutils/measures.py
medutils/mri.py
medutils/visualization.py
medutils/optimization/__init__.py
medutils/optimization/base_optimizer.py
medutils/optimization/cgsense.py
medutils/optimization/nabla.py
medutils/optimization/optimizer.py
medutils/optimization/prox.py
medutils/optimization/recon_optimizer.py
medutils/optimization/stepsize.py
medutils/optimization/utils.py
medutils/optimization_th/__init__.py
medutils/optimization_th/nabla_th.py
medutils/optimization_th/optimizer_th.py
medutils/optimization_th/prox_th.py
medutils/optimization_th/recon_optimizer_th.py
medutils_mri-0.1.1.dist-info/LICENSE
medutils_mri-0.1.1.dist-info/METADATA
medutils_mri-0.1.1.dist-info/WHEEL
medutils_mri-0.1.1.dist-info/top_level.txt
medutils_mri-0.1.1.dist-info/RECORD
