Metadata-Version: 2.1
Name: medutils-mri
Version: 0.1.1
Summary: Utils for medical image processing and reconstruction
Home-page: https://github.com/khammernik/medutils/
Author: Kerstin Hammernik
Author-email: k.hammernik@tum.de
License: Apache 2.0
Classifier: Development Status :: 4 - Beta
Classifier: Intended Audience :: Science/Research
Classifier: License :: OSI Approved :: Apache Software License
Classifier: Operating System :: Unix
Classifier: Programming Language :: Python :: 3.6
License-File: LICENSE
Requires-Dist: numpy
Requires-Dist: scipy
Requires-Dist: h5py
Requires-Dist: matplotlib
Requires-Dist: scikit-image
